{
  "yield-curves" : {
    "transaction" : "yield-curves",
    "sampleCount" : 241,
    "errorCount" : 241,
    "errorPct" : 100.0,
    "meanResTime" : 97.08713692946061,
    "medianResTime" : 92.0,
    "minResTime" : 79.0,
    "maxResTime" : 725.0,
    "pct1ResTime" : 108.80000000000001,
    "pct2ResTime" : 116.0,
    "pct3ResTime" : 147.31999999999994,
    "throughput" : 4.040031515598545,
    "receivedKBytesPerSec" : 3.764626910004526,
    "sentKBytesPerSec" : 0.9587184162992641
  },
  "tradable-securities-uuid" : {
    "transaction" : "tradable-securities-uuid",
    "sampleCount" : 1235,
    "errorCount" : 1235,
    "errorPct" : 100.0,
    "meanResTime" : 95.9805668016195,
    "medianResTime" : 93.0,
    "minResTime" : 78.0,
    "maxResTime" : 700.0,
    "pct1ResTime" : 109.0,
    "pct2ResTime" : 114.0,
    "pct3ResTime" : 135.9200000000003,
    "throughput" : 20.634231103388355,
    "receivedKBytesPerSec" : 19.225564334734013,
    "sentKBytesPerSec" : 3.707713401390096
  },
  "appraiser-5-tickers-dinamico" : {
    "transaction" : "appraiser-5-tickers-dinamico",
    "sampleCount" : 602,
    "errorCount" : 602,
    "errorPct" : 100.0,
    "meanResTime" : 94.65116279069767,
    "medianResTime" : 92.0,
    "minResTime" : 78.0,
    "maxResTime" : 257.0,
    "pct1ResTime" : 107.0,
    "pct2ResTime" : 112.0,
    "pct3ResTime" : 125.91000000000008,
    "throughput" : 10.300106080826746,
    "receivedKBytesPerSec" : 9.602981544930364,
    "sentKBytesPerSec" : 11.632131582999692
  },
  "bond-payment-forecast-cashflow" : {
    "transaction" : "bond-payment-forecast-cashflow",
    "sampleCount" : 1216,
    "errorCount" : 1216,
    "errorPct" : 100.0,
    "meanResTime" : 97.57894736842103,
    "medianResTime" : 94.0,
    "minResTime" : 79.0,
    "maxResTime" : 731.0,
    "pct1ResTime" : 111.0,
    "pct2ResTime" : 117.0,
    "pct3ResTime" : 142.82999999999993,
    "throughput" : 20.28932307743647,
    "receivedKBytesPerSec" : 18.927760348013614,
    "sentKBytesPerSec" : 10.441868419735371
  },
  "investments-metrics" : {
    "transaction" : "investments-metrics",
    "sampleCount" : 505,
    "errorCount" : 505,
    "errorPct" : 100.0,
    "meanResTime" : 95.73465346534653,
    "medianResTime" : 92.0,
    "minResTime" : 78.0,
    "maxResTime" : 703.0,
    "pct1ResTime" : 108.0,
    "pct2ResTime" : 113.69999999999999,
    "pct3ResTime" : 137.94,
    "throughput" : 8.430999365588168,
    "receivedKBytesPerSec" : 7.854400658202277,
    "sentKBytesPerSec" : 1.226776274875622
  },
  "investments-exchange-rate-sensitivity" : {
    "transaction" : "investments-exchange-rate-sensitivity",
    "sampleCount" : 24,
    "errorCount" : 24,
    "errorPct" : 100.0,
    "meanResTime" : 121.66666666666664,
    "medianResTime" : 92.0,
    "minResTime" : 83.0,
    "maxResTime" : 708.0,
    "pct1ResTime" : 139.0,
    "pct2ResTime" : 569.75,
    "pct3ResTime" : 708.0,
    "throughput" : 0.42337002540220153,
    "receivedKBytesPerSec" : 0.39427367233806093,
    "sentKBytesPerSec" : 0.07690119602032176
  },
  "bond-laws" : {
    "transaction" : "bond-laws",
    "sampleCount" : 31,
    "errorCount" : 31,
    "errorPct" : 100.0,
    "meanResTime" : 93.38709677419355,
    "medianResTime" : 92.0,
    "minResTime" : 83.0,
    "maxResTime" : 110.0,
    "pct1ResTime" : 105.0,
    "pct2ResTime" : 107.6,
    "pct3ResTime" : 110.0,
    "throughput" : 0.5765403857241161,
    "receivedKBytesPerSec" : 0.5369286612639254,
    "sentKBytesPerSec" : 0.07713479769941788
  },
  "yield-curves-uuid-metrics" : {
    "transaction" : "yield-curves-uuid-metrics",
    "sampleCount" : 595,
    "errorCount" : 595,
    "errorPct" : 100.0,
    "meanResTime" : 94.81680672268908,
    "medianResTime" : 91.0,
    "minResTime" : 78.0,
    "maxResTime" : 724.0,
    "pct1ResTime" : 106.0,
    "pct2ResTime" : 112.19999999999993,
    "pct3ResTime" : 130.15999999999985,
    "throughput" : 9.935378295790406,
    "receivedKBytesPerSec" : 9.25755550557717,
    "sentKBytesPerSec" : 2.4838445739476014
  },
  "investments" : {
    "transaction" : "investments",
    "sampleCount" : 1243,
    "errorCount" : 1243,
    "errorPct" : 100.0,
    "meanResTime" : 95.37409493161695,
    "medianResTime" : 92.0,
    "minResTime" : 78.0,
    "maxResTime" : 707.0,
    "pct1ResTime" : 109.0,
    "pct2ResTime" : 114.0,
    "pct3ResTime" : 133.0,
    "throughput" : 20.75021284409796,
    "receivedKBytesPerSec" : 19.352543121796906,
    "sentKBytesPerSec" : 8.916107081448342
  },
  "instrument-issuers" : {
    "transaction" : "instrument-issuers",
    "sampleCount" : 30,
    "errorCount" : 30,
    "errorPct" : 100.0,
    "meanResTime" : 119.7333333333333,
    "medianResTime" : 93.5,
    "minResTime" : 83.0,
    "maxResTime" : 736.0,
    "pct1ResTime" : 136.8,
    "pct2ResTime" : 413.1499999999996,
    "pct3ResTime" : 736.0,
    "throughput" : 0.508785021368971,
    "receivedKBytesPerSec" : 0.47519726019265995,
    "sentKBytesPerSec" : 0.0725416143748728
  },
  "currencies-uuid" : {
    "transaction" : "currencies-uuid",
    "sampleCount" : 1222,
    "errorCount" : 1222,
    "errorPct" : 100.0,
    "meanResTime" : 97.06873977086727,
    "medianResTime" : 94.0,
    "minResTime" : 79.0,
    "maxResTime" : 726.0,
    "pct1ResTime" : 110.0,
    "pct2ResTime" : 118.0,
    "pct3ResTime" : 144.53999999999996,
    "throughput" : 20.386713601708347,
    "receivedKBytesPerSec" : 18.995159693490265,
    "sentKBytesPerSec" : 4.678591500392052
  },
  "investments-price-sensitivity" : {
    "transaction" : "investments-price-sensitivity",
    "sampleCount" : 120,
    "errorCount" : 120,
    "errorPct" : 100.0,
    "meanResTime" : 100.42499999999998,
    "medianResTime" : 93.0,
    "minResTime" : 78.0,
    "maxResTime" : 701.0,
    "pct1ResTime" : 107.0,
    "pct2ResTime" : 112.89999999999998,
    "pct3ResTime" : 588.0199999999957,
    "throughput" : 2.052931414982978,
    "receivedKBytesPerSec" : 1.9145155883786973,
    "sentKBytesPerSec" : 0.36287166612492083
  },
  "bonds-coupons" : {
    "transaction" : "bonds-coupons",
    "sampleCount" : 263,
    "errorCount" : 263,
    "errorPct" : 100.0,
    "meanResTime" : 102.98098859315593,
    "medianResTime" : 94.0,
    "minResTime" : 80.0,
    "maxResTime" : 1084.0,
    "pct1ResTime" : 112.0,
    "pct2ResTime" : 120.59999999999997,
    "pct3ResTime" : 398.12000000000705,
    "throughput" : 4.395200374344062,
    "receivedKBytesPerSec" : 4.096901477739897,
    "sentKBytesPerSec" : 0.7640094400715265
  },
  "markets-uuid" : {
    "transaction" : "markets-uuid",
    "sampleCount" : 1230,
    "errorCount" : 1230,
    "errorPct" : 100.0,
    "meanResTime" : 96.48373983739819,
    "medianResTime" : 93.0,
    "minResTime" : 79.0,
    "maxResTime" : 738.0,
    "pct1ResTime" : 109.0,
    "pct2ResTime" : 115.0,
    "pct3ResTime" : 142.3800000000001,
    "throughput" : 20.50546812483329,
    "receivedKBytesPerSec" : 19.109864844166776,
    "sentKBytesPerSec" : 3.4442778490930914
  },
  "tradable-securities-params" : {
    "transaction" : "tradable-securities-params",
    "sampleCount" : 1243,
    "errorCount" : 1243,
    "errorPct" : 100.0,
    "meanResTime" : 95.32421560740156,
    "medianResTime" : 92.0,
    "minResTime" : 77.0,
    "maxResTime" : 700.0,
    "pct1ResTime" : 107.0,
    "pct2ResTime" : 113.0,
    "pct3ResTime" : 134.55999999999995,
    "throughput" : 20.764424843807422,
    "receivedKBytesPerSec" : 19.3469067396679,
    "sentKBytesPerSec" : 4.035273968669607
  },
  "debt-types" : {
    "transaction" : "debt-types",
    "sampleCount" : 30,
    "errorCount" : 30,
    "errorPct" : 100.0,
    "meanResTime" : 95.89999999999999,
    "medianResTime" : 93.5,
    "minResTime" : 82.0,
    "maxResTime" : 114.0,
    "pct1ResTime" : 109.7,
    "pct2ResTime" : 112.9,
    "pct3ResTime" : 114.0,
    "throughput" : 0.5400928959781083,
    "receivedKBytesPerSec" : 0.5031549020181472,
    "sentKBytesPerSec" : 0.07278595668454975
  },
  "tradable-securities-metrics" : {
    "transaction" : "tradable-securities-metrics",
    "sampleCount" : 1234,
    "errorCount" : 1234,
    "errorPct" : 100.0,
    "meanResTime" : 96.00162074554297,
    "medianResTime" : 93.0,
    "minResTime" : 77.0,
    "maxResTime" : 699.0,
    "pct1ResTime" : 109.0,
    "pct2ResTime" : 116.0,
    "pct3ResTime" : 135.6500000000001,
    "throughput" : 20.61270170046437,
    "receivedKBytesPerSec" : 19.206778602420407,
    "sentKBytesPerSec" : 3.8648815688370695
  },
  "bonds-uuid" : {
    "transaction" : "bonds-uuid",
    "sampleCount" : 1217,
    "errorCount" : 1217,
    "errorPct" : 100.0,
    "meanResTime" : 97.41166803615438,
    "medianResTime" : 94.0,
    "minResTime" : 79.0,
    "maxResTime" : 733.0,
    "pct1ResTime" : 110.0,
    "pct2ResTime" : 118.0,
    "pct3ResTime" : 151.63999999999987,
    "throughput" : 20.3334892735414,
    "receivedKBytesPerSec" : 18.94675159664673,
    "sentKBytesPerSec" : 4.765661548486267
  },
  "bond-screener-filter" : {
    "transaction" : "bond-screener-filter",
    "sampleCount" : 30,
    "errorCount" : 30,
    "errorPct" : 100.0,
    "meanResTime" : 92.10000000000001,
    "medianResTime" : 90.0,
    "minResTime" : 80.0,
    "maxResTime" : 109.0,
    "pct1ResTime" : 102.9,
    "pct2ResTime" : 109.0,
    "pct3ResTime" : 109.0,
    "throughput" : 0.5388511693070374,
    "receivedKBytesPerSec" : 0.5018402328735136,
    "sentKBytesPerSec" : 0.37730106288393145
  },
  "yield-curves-uuid" : {
    "transaction" : "yield-curves-uuid",
    "sampleCount" : 598,
    "errorCount" : 598,
    "errorPct" : 100.0,
    "meanResTime" : 94.50501672240797,
    "medianResTime" : 91.0,
    "minResTime" : 78.0,
    "maxResTime" : 722.0,
    "pct1ResTime" : 106.0,
    "pct2ResTime" : 111.0,
    "pct3ResTime" : 133.07999999999993,
    "throughput" : 9.98113931867875,
    "receivedKBytesPerSec" : 9.29950315979003,
    "sentKBytesPerSec" : 2.729217782451221
  },
  "Total" : {
    "transaction" : "Total",
    "sampleCount" : 15624,
    "errorCount" : 15624,
    "errorPct" : 100.0,
    "meanResTime" : 96.59491807475699,
    "medianResTime" : 93.0,
    "minResTime" : 77.0,
    "maxResTime" : 1084.0,
    "pct1ResTime" : 109.0,
    "pct2ResTime" : 115.0,
    "pct3ResTime" : 141.0,
    "throughput" : 257.37159424109643,
    "receivedKBytesPerSec" : 239.8814316130201,
    "sentKBytesPerSec" : 88.13105762815866
  },
  "investments-irr-sensitivity" : {
    "transaction" : "investments-irr-sensitivity",
    "sampleCount" : 20,
    "errorCount" : 20,
    "errorPct" : 100.0,
    "meanResTime" : 95.0,
    "medianResTime" : 91.0,
    "minResTime" : 81.0,
    "maxResTime" : 122.0,
    "pct1ResTime" : 112.9,
    "pct2ResTime" : 121.55,
    "pct3ResTime" : 122.0,
    "throughput" : 0.36359008853418656,
    "receivedKBytesPerSec" : 0.33832696861308564,
    "sentKBytesPerSec" : 0.06249204646681332
  },
  "bond-payment-forecast" : {
    "transaction" : "bond-payment-forecast",
    "sampleCount" : 1219,
    "errorCount" : 1219,
    "errorPct" : 100.0,
    "meanResTime" : 97.35849056603766,
    "medianResTime" : 94.0,
    "minResTime" : 79.0,
    "maxResTime" : 733.0,
    "pct1ResTime" : 111.0,
    "pct2ResTime" : 118.0,
    "pct3ResTime" : 143.5999999999999,
    "throughput" : 20.33225472862528,
    "receivedKBytesPerSec" : 18.965484214981487,
    "sentKBytesPerSec" : 20.01456324849051
  },
  "bonds-payment-summary" : {
    "transaction" : "bonds-payment-summary",
    "sampleCount" : 221,
    "errorCount" : 221,
    "errorPct" : 100.0,
    "meanResTime" : 100.24886877828048,
    "medianResTime" : 95.0,
    "minResTime" : 78.0,
    "maxResTime" : 731.0,
    "pct1ResTime" : 114.0,
    "pct2ResTime" : 122.79999999999995,
    "pct3ResTime" : 158.82000000000002,
    "throughput" : 3.7041382431322596,
    "receivedKBytesPerSec" : 3.451694962749108,
    "sentKBytesPerSec" : 1.0490235258870657
  },
  "bonds-issue-conditions" : {
    "transaction" : "bonds-issue-conditions",
    "sampleCount" : 1224,
    "errorCount" : 1224,
    "errorPct" : 100.0,
    "meanResTime" : 96.8815359477124,
    "medianResTime" : 93.0,
    "minResTime" : 79.0,
    "maxResTime" : 733.0,
    "pct1ResTime" : 109.0,
    "pct2ResTime" : 114.0,
    "pct3ResTime" : 146.0,
    "throughput" : 20.436103783350585,
    "receivedKBytesPerSec" : 19.04156653316693,
    "sentKBytesPerSec" : 3.7319837963735933
  },
  "currencies" : {
    "transaction" : "currencies",
    "sampleCount" : 31,
    "errorCount" : 31,
    "errorPct" : 100.0,
    "meanResTime" : 113.09677419354843,
    "medianResTime" : 90.0,
    "minResTime" : 82.0,
    "maxResTime" : 698.0,
    "pct1ResTime" : 106.6,
    "pct2ResTime" : 351.79999999999916,
    "pct3ResTime" : 698.0,
    "throughput" : 0.5192542838478418,
    "receivedKBytesPerSec" : 0.48408553667442755,
    "sentKBytesPerSec" : 0.10040268379089128
  }
}