{
  "tradable-securities-uuid" : {
    "transaction" : "tradable-securities-uuid",
    "sampleCount" : 1228,
    "errorCount" : 1228,
    "errorPct" : 100.0,
    "meanResTime" : 96.49429967426705,
    "medianResTime" : 92.0,
    "minResTime" : 79.0,
    "maxResTime" : 1101.0,
    "pct1ResTime" : 108.0,
    "pct2ResTime" : 114.0,
    "pct3ResTime" : 138.71000000000004,
    "throughput" : 20.5056273586481,
    "receivedKBytesPerSec" : 16.584749957210366,
    "sentKBytesPerSec" : 3.6846049160070797
  },
  "yield-curves" : {
    "transaction" : "yield-curves",
    "sampleCount" : 240,
    "errorCount" : 240,
    "errorPct" : 100.0,
    "meanResTime" : 105.55416666666673,
    "medianResTime" : 92.0,
    "minResTime" : 79.0,
    "maxResTime" : 911.0,
    "pct1ResTime" : 111.0,
    "pct2ResTime" : 233.39999999999986,
    "pct3ResTime" : 296.49,
    "throughput" : 4.035919685198264,
    "receivedKBytesPerSec" : 3.263452277351764,
    "sentKBytesPerSec" : 0.9577426596710725
  },
  "appraiser-5-tickers-dinamico" : {
    "transaction" : "appraiser-5-tickers-dinamico",
    "sampleCount" : 591,
    "errorCount" : 591,
    "errorPct" : 100.0,
    "meanResTime" : 98.32148900169196,
    "medianResTime" : 92.0,
    "minResTime" : 78.0,
    "maxResTime" : 295.0,
    "pct1ResTime" : 108.0,
    "pct2ResTime" : 116.79999999999995,
    "pct3ResTime" : 268.5600000000003,
    "throughput" : 10.091868447115878,
    "receivedKBytesPerSec" : 8.17211152816673,
    "sentKBytesPerSec" : 11.39759264219972
  },
  "investments-metrics" : {
    "transaction" : "investments-metrics",
    "sampleCount" : 504,
    "errorCount" : 504,
    "errorPct" : 100.0,
    "meanResTime" : 98.15476190476187,
    "medianResTime" : 93.0,
    "minResTime" : 80.0,
    "maxResTime" : 701.0,
    "pct1ResTime" : 110.0,
    "pct2ResTime" : 120.0,
    "pct3ResTime" : 216.49999999999943,
    "throughput" : 8.415990381725278,
    "receivedKBytesPerSec" : 6.805182450823231,
    "sentKBytesPerSec" : 1.224592350465885
  },
  "bond-payment-forecast-cashflow" : {
    "transaction" : "bond-payment-forecast-cashflow",
    "sampleCount" : 2228,
    "errorCount" : 2228,
    "errorPct" : 100.0,
    "meanResTime" : 52.890035906642716,
    "medianResTime" : 49.0,
    "minResTime" : 32.0,
    "maxResTime" : 680.0,
    "pct1ResTime" : 69.0,
    "pct2ResTime" : 78.54999999999973,
    "pct3ResTime" : 113.42000000000007,
    "throughput" : 37.231375956685945,
    "receivedKBytesPerSec" : 30.141922557526488,
    "sentKBytesPerSec" : 19.161069462083486
  },
  "investments-exchange-rate-sensitivity" : {
    "transaction" : "investments-exchange-rate-sensitivity",
    "sampleCount" : 24,
    "errorCount" : 24,
    "errorPct" : 100.0,
    "meanResTime" : 95.79166666666667,
    "medianResTime" : 95.5,
    "minResTime" : 82.0,
    "maxResTime" : 123.0,
    "pct1ResTime" : 114.0,
    "pct2ResTime" : 120.75,
    "pct3ResTime" : 123.0,
    "throughput" : 0.4574914220358368,
    "receivedKBytesPerSec" : 0.3700177814048799,
    "sentKBytesPerSec" : 0.08309902783072817
  },
  "bond-laws" : {
    "transaction" : "bond-laws",
    "sampleCount" : 30,
    "errorCount" : 30,
    "errorPct" : 100.0,
    "meanResTime" : 48.33333333333333,
    "medianResTime" : 46.0,
    "minResTime" : 36.0,
    "maxResTime" : 81.0,
    "pct1ResTime" : 65.60000000000001,
    "pct2ResTime" : 73.29999999999998,
    "pct3ResTime" : 81.0,
    "throughput" : 0.5494505494505495,
    "receivedKBytesPerSec" : 0.44421073717948717,
    "sentKBytesPerSec" : 0.0735104739010989
  },
  "yield-curves-uuid-metrics" : {
    "transaction" : "yield-curves-uuid-metrics",
    "sampleCount" : 599,
    "errorCount" : 599,
    "errorPct" : 100.0,
    "meanResTime" : 99.57595993322218,
    "medianResTime" : 92.0,
    "minResTime" : 79.0,
    "maxResTime" : 958.0,
    "pct1ResTime" : 107.0,
    "pct2ResTime" : 114.0,
    "pct3ResTime" : 258.0,
    "throughput" : 10.004509545204016,
    "receivedKBytesPerSec" : 8.089371852713244,
    "sentKBytesPerSec" : 2.501127386301004
  },
  "investments" : {
    "transaction" : "investments",
    "sampleCount" : 1235,
    "errorCount" : 1235,
    "errorPct" : 100.0,
    "meanResTime" : 95.9295546558704,
    "medianResTime" : 92.0,
    "minResTime" : 79.0,
    "maxResTime" : 697.0,
    "pct1ResTime" : 108.0,
    "pct2ResTime" : 114.0,
    "pct3ResTime" : 139.6400000000001,
    "throughput" : 20.614942912465782,
    "receivedKBytesPerSec" : 16.692880906974025,
    "sentKBytesPerSec" : 8.85798328270014
  },
  "currencies-uuid" : {
    "transaction" : "currencies-uuid",
    "sampleCount" : 2243,
    "errorCount" : 2243,
    "errorPct" : 100.0,
    "meanResTime" : 52.560855996433226,
    "medianResTime" : 49.0,
    "minResTime" : 32.0,
    "maxResTime" : 680.0,
    "pct1ResTime" : 68.0,
    "pct2ResTime" : 77.0,
    "pct3ResTime" : 108.55999999999995,
    "throughput" : 37.417008641110336,
    "receivedKBytesPerSec" : 30.2510703643696,
    "sentKBytesPerSec" : 8.586911162754813
  },
  "instrument-issuers" : {
    "transaction" : "instrument-issuers",
    "sampleCount" : 30,
    "errorCount" : 30,
    "errorPct" : 100.0,
    "meanResTime" : 56.43333333333333,
    "medianResTime" : 51.0,
    "minResTime" : 36.0,
    "maxResTime" : 152.0,
    "pct1ResTime" : 85.90000000000005,
    "pct2ResTime" : 117.89999999999995,
    "pct3ResTime" : 152.0,
    "throughput" : 0.5277044854881267,
    "receivedKBytesPerSec" : 0.427660510114336,
    "sentKBytesPerSec" : 0.0752391160949868
  },
  "investments-price-sensitivity" : {
    "transaction" : "investments-price-sensitivity",
    "sampleCount" : 122,
    "errorCount" : 122,
    "errorPct" : 100.0,
    "meanResTime" : 95.11475409836065,
    "medianResTime" : 93.0,
    "minResTime" : 81.0,
    "maxResTime" : 210.0,
    "pct1ResTime" : 106.0,
    "pct2ResTime" : 109.69999999999999,
    "pct3ResTime" : 196.65999999999977,
    "throughput" : 2.0582727380088746,
    "receivedKBytesPerSec" : 1.6640263853272146,
    "sentKBytesPerSec" : 0.3638157866988342
  },
  "bonds-coupons" : {
    "transaction" : "bonds-coupons",
    "sampleCount" : 260,
    "errorCount" : 260,
    "errorPct" : 100.0,
    "meanResTime" : 55.657692307692315,
    "medianResTime" : 47.0,
    "minResTime" : 34.0,
    "maxResTime" : 680.0,
    "pct1ResTime" : 69.9,
    "pct2ResTime" : 91.94999999999999,
    "pct3ResTime" : 149.67999999999984,
    "throughput" : 4.377546553523925,
    "receivedKBytesPerSec" : 3.541909352165202,
    "sentKBytesPerSec" : 0.7609407094992761
  },
  "tradable-securities-params" : {
    "transaction" : "tradable-securities-params",
    "sampleCount" : 1244,
    "errorCount" : 1244,
    "errorPct" : 100.0,
    "meanResTime" : 95.20418006430864,
    "medianResTime" : 92.0,
    "minResTime" : 79.0,
    "maxResTime" : 711.0,
    "pct1ResTime" : 107.0,
    "pct2ResTime" : 111.0,
    "pct3ResTime" : 132.54999999999995,
    "throughput" : 20.770720630468176,
    "receivedKBytesPerSec" : 16.79799354984806,
    "sentKBytesPerSec" : 4.036497466272624
  },
  "markets-uuid" : {
    "transaction" : "markets-uuid",
    "sampleCount" : 2241,
    "errorCount" : 2241,
    "errorPct" : 100.0,
    "meanResTime" : 52.66086568496203,
    "medianResTime" : 49.0,
    "minResTime" : 33.0,
    "maxResTime" : 696.0,
    "pct1ResTime" : 69.0,
    "pct2ResTime" : 78.0,
    "pct3ResTime" : 106.0,
    "throughput" : 37.395497855724464,
    "receivedKBytesPerSec" : 30.231817852345355,
    "sentKBytesPerSec" : 6.281275030453719
  },
  "debt-types" : {
    "transaction" : "debt-types",
    "sampleCount" : 30,
    "errorCount" : 30,
    "errorPct" : 100.0,
    "meanResTime" : 48.03333333333333,
    "medianResTime" : 45.5,
    "minResTime" : 37.0,
    "maxResTime" : 76.0,
    "pct1ResTime" : 62.0,
    "pct2ResTime" : 70.5,
    "pct3ResTime" : 76.0,
    "throughput" : 0.5527814118037258,
    "receivedKBytesPerSec" : 0.44737146680547624,
    "sentKBytesPerSec" : 0.07449593245011148
  },
  "tradable-securities-metrics" : {
    "transaction" : "tradable-securities-metrics",
    "sampleCount" : 1225,
    "errorCount" : 1225,
    "errorPct" : 100.0,
    "meanResTime" : 96.67428571428583,
    "medianResTime" : 93.0,
    "minResTime" : 79.0,
    "maxResTime" : 1115.0,
    "pct1ResTime" : 109.0,
    "pct2ResTime" : 114.0,
    "pct3ResTime" : 136.74,
    "throughput" : 20.465100738414247,
    "receivedKBytesPerSec" : 16.54813201138528,
    "sentKBytesPerSec" : 3.8372063884526715
  },
  "bonds-uuid" : {
    "transaction" : "bonds-uuid",
    "sampleCount" : 2227,
    "errorCount" : 2227,
    "errorPct" : 100.0,
    "meanResTime" : 52.852716659182896,
    "medianResTime" : 49.0,
    "minResTime" : 34.0,
    "maxResTime" : 680.0,
    "pct1ResTime" : 70.0,
    "pct2ResTime" : 78.0,
    "pct3ResTime" : 107.0,
    "throughput" : 37.251392536339765,
    "receivedKBytesPerSec" : 30.121880253374705,
    "sentKBytesPerSec" : 8.730795125704631
  },
  "bond-screener-filter" : {
    "transaction" : "bond-screener-filter",
    "sampleCount" : 31,
    "errorCount" : 31,
    "errorPct" : 100.0,
    "meanResTime" : 51.35483870967742,
    "medianResTime" : 50.0,
    "minResTime" : 34.0,
    "maxResTime" : 97.0,
    "pct1ResTime" : 73.2,
    "pct2ResTime" : 88.59999999999998,
    "pct3ResTime" : 97.0,
    "throughput" : 0.5339488098108788,
    "receivedKBytesPerSec" : 0.4320840797133901,
    "sentKBytesPerSec" : 0.3738684537445313
  },
  "yield-curves-uuid" : {
    "transaction" : "yield-curves-uuid",
    "sampleCount" : 597,
    "errorCount" : 597,
    "errorPct" : 100.0,
    "meanResTime" : 99.86599664991624,
    "medianResTime" : 92.0,
    "minResTime" : 80.0,
    "maxResTime" : 938.0,
    "pct1ResTime" : 108.0,
    "pct2ResTime" : 115.10000000000002,
    "pct3ResTime" : 281.15999999999985,
    "throughput" : 9.978438549867121,
    "receivedKBytesPerSec" : 8.064797824842467,
    "sentKBytesPerSec" : 2.728479290979291
  },
  "Total" : {
    "transaction" : "Total",
    "sampleCount" : 21249,
    "errorCount" : 21249,
    "errorPct" : 100.0,
    "meanResTime" : 68.81062638241826,
    "medianResTime" : 57.0,
    "minResTime" : 32.0,
    "maxResTime" : 1115.0,
    "pct1ResTime" : 95.0,
    "pct2ResTime" : 100.0,
    "pct3ResTime" : 105.0,
    "throughput" : 234.77223259565346,
    "receivedKBytesPerSec" : 189.89594396344563,
    "sentKBytesPerSec" : 80.23017306980522
  },
  "investments-irr-sensitivity" : {
    "transaction" : "investments-irr-sensitivity",
    "sampleCount" : 20,
    "errorCount" : 20,
    "errorPct" : 100.0,
    "meanResTime" : 94.64999999999999,
    "medianResTime" : 93.0,
    "minResTime" : 82.0,
    "maxResTime" : 110.0,
    "pct1ResTime" : 109.9,
    "pct2ResTime" : 110.0,
    "pct3ResTime" : 110.0,
    "throughput" : 0.3518648838845883,
    "receivedKBytesPerSec" : 0.2846875549788881,
    "sentKBytesPerSec" : 0.060476776917663615
  },
  "bond-payment-forecast" : {
    "transaction" : "bond-payment-forecast",
    "sampleCount" : 1811,
    "errorCount" : 1811,
    "errorPct" : 100.0,
    "meanResTime" : 53.32799558255105,
    "medianResTime" : 49.0,
    "minResTime" : 33.0,
    "maxResTime" : 679.0,
    "pct1ResTime" : 71.0,
    "pct2ResTime" : 81.0,
    "pct3ResTime" : 121.0,
    "throughput" : 30.251398981040676,
    "receivedKBytesPerSec" : 24.490210395264345,
    "sentKBytesPerSec" : 29.778720871961912
  },
  "bonds-payment-summary" : {
    "transaction" : "bonds-payment-summary",
    "sampleCount" : 220,
    "errorCount" : 220,
    "errorPct" : 100.0,
    "meanResTime" : 55.83181818181819,
    "medianResTime" : 47.0,
    "minResTime" : 33.0,
    "maxResTime" : 680.0,
    "pct1ResTime" : 69.0,
    "pct2ResTime" : 89.89999999999998,
    "pct3ResTime" : 180.27999999999975,
    "throughput" : 3.722882187700951,
    "receivedKBytesPerSec" : 3.0104314735844584,
    "sentKBytesPerSec" : 1.0543318695637458
  },
  "bonds-issue-conditions" : {
    "transaction" : "bonds-issue-conditions",
    "sampleCount" : 2239,
    "errorCount" : 2239,
    "errorPct" : 100.0,
    "meanResTime" : 52.63555158552925,
    "medianResTime" : 49.0,
    "minResTime" : 33.0,
    "maxResTime" : 681.0,
    "pct1ResTime" : 69.0,
    "pct2ResTime" : 78.0,
    "pct3ResTime" : 108.0,
    "throughput" : 37.433959740520294,
    "receivedKBytesPerSec" : 30.26179620623788,
    "sentKBytesPerSec" : 6.836084444802046
  },
  "currencies" : {
    "transaction" : "currencies",
    "sampleCount" : 30,
    "errorCount" : 30,
    "errorPct" : 100.0,
    "meanResTime" : 51.63333333333334,
    "medianResTime" : 48.0,
    "minResTime" : 35.0,
    "maxResTime" : 99.0,
    "pct1ResTime" : 77.70000000000003,
    "pct2ResTime" : 93.5,
    "pct3ResTime" : 99.0,
    "throughput" : 0.5407256538274364,
    "receivedKBytesPerSec" : 0.4366993317532128,
    "sentKBytesPerSec" : 0.10455437447053946
  }
}